_softfloat.so
softfloat.py
softfloat-0.1.4.1.data/data/LICENSE
softfloat-0.1.4.1.dist-info/RECORD
softfloat-0.1.4.1.dist-info/WHEEL
softfloat-0.1.4.1.dist-info/METADATA
softfloat-0.1.4.1.dist-info/top_level.txt
softfloat-0.1.4.1.dist-info/LICENSE.txt
